Workbook

Sheet Cost and Budget Tracking
A1: Category | B1: Item Description | C1: Supplier | D1: Quantity | E1: Unit Cost | F1: Total Cost | G1: Budgeted Amount | H1: Variance | I1: Payment Status | J1: Notes
A2: design | B2: Architectural Design Fees | C2: Stephenson-Edwards Studio | D2: 1 | E2: 25000 | F2: =D2*E2 -> 25000 | G2: 28000 | H2: =G2-F2 -> 3000 | I2: paid | J2: Final burrow layout approved Apr 5
A3: design | B3: Interior Design Services | C3: Tokkia Design Partners | D3: 1 | E3: 18000 | F3: =D3*E3 -> 18000 | G3: 20000 | H3: =G3-F3 -> 2000 | I3: paid | J3: Terrazzo & lime-wash specs Apr 10
A4: engineering & consulting | B4: Structural Engineering | C4: EngStruct London | D4: 1 | E4: 8000 | F4: =D4*E4 -> 8000 | G4: 9000 | H4: =G4-F4 -> 1000 | I4: pending | J4: Low-ceiling analysis complete Apr 12
A5: engineering & consulting | B5: MEP Engineering Plans | C5: MechEng UK | D5: 1 | E5: 6500 | F5: =D5*E5 -> 6500 | G5: 7000 | H5: =G5-F5 -> 500 | I5: paid | J5: Ventilation for matcha stations Apr 15
A6: permits & approvals | B6: Planning Application | C6: Camden Council | D6: 1 | E6: 4000 | F6: =D6*E6 -> 4000 | G6: 4500 | H6: =G6-F6 -> 500 | I6: paid | J6: Covent Garden heritage ok Apr 8
A7: permits & approvals | B7: Building Regs Approval | C7: LABC London | D7: 1 | E7: 2500 | F7: =D7*E7 -> 2500 | G7: 2800 | H7: =G7-F7 -> 300 | I7: paid | J7: Food-safe compliance Apr 18
A8: permits & approvals | B8: Site Surveys | C8: SurveyPro Ltd | D8: 1 | E8: 3000 | F8: =D8*E8 -> 3000 | G8: 3200 | H8: =G8-F8 -> 200 | I8: paid | J8: Monmouth St measurements Apr 3
A9: design | B9: 3D Renderings | C9: RenderHub Studio | D9: 1 | E9: 5000 | F9: =D9*E9 -> 5000 | G9: 5500 | H9: =G9-F9 -> 500 | I9: pending | J9: Bunny-themed visuals delivered Apr 20
A10: engineering & consulting | B10: Landscape Consultant | C10: GreenSpace Assoc | D10: 1 | E10: 2000 | F10: =D10*E10 -> 2000 | G10: 2200 | H10: =G10-F10 -> 200 | I10: paid | J10: Street-facing tweaks Apr 7
A11: design | B11: Acoustic Design | C11: SoundEng Ltd | D11: 1 | E11: 3500 | F11: =D11*E11 -> 3500 | G11: 3800 | H11: =G11-F11 -> 300 | I11: pending | J11: Calming ambiance plans Apr 22
A12: engineering & consulting | B12: Sustainability Audit | C12: EcoBuild Partners | D12: 1 | E12: 4000 | F12: =D12*E12 -> 4000 | G12: 4200 | H12: =G12-F12 -> 200 | I12: paid | J12: Energy standards met Apr 14
A13: design | B13: Quantity Surveyor | C13: QS Experts | D13: 1 | E13: 7000 | F13: =D13*E13 -> 7000 | G13: 7500 | H13: =G13-F13 -> 500 | I13: paid | J13: Initial cost plan Apr 9
... A28: fixtures & equipment | B28: Courier Deliveries | C28: DHL UK | D28: 12 | E28: 45 | F28: =D28*E28 -> 540 | G28: 600 | H28: =G28-F28 -> 60 | I28: paid | J28: Docs to council Apr 10-26
F30: =SUM(F2:F28) -> 154040 | G30: =SUM(G2:G28) -> 169100 | H30: =SUM(H2:H28) -> 15060 | I30: =COUNTIF(I2:I28,"Paid")&" Paid / "&COUNTA(I2:I28)&" Total" -> 19 Paid / 27 Total | J30: =IF(H30>0,"Under Budget by £"&H30,"Over Budget by £"&-H30) -> Under Budget by £15060

Sheet Contractor and Labor Management
A1: Contractor | B1: Role | C1: Task | D1: Start Date | E1: End Date | F1: Contract Value | G1: Amount Paid | H1: Remaining Balance | I1: Status | J1: Required Materials | K1: Key Delivery Date | L1: Delivery Status
A2: Stephenson Edwards Studio | B2: Architect | C2: Architectural Design Fees | D2: 46113 | E2: 46117 | F2: 25000 | G2: 25000 | H2: =F2-G2 -> 0 | I2: paid | J2: =IF(OR(A2="EcoBuild Ltd",B2="Carpenter"),"Bamboo Floor Planks", IF(OR(A2="TerraFloor Supplies"),"Terrazzo Tiles, Terrazzo Sample Set", IF(OR(A2="EcoPaints UK"),"Lime-Wash Paint", IF(OR(A2="Lumina Studio",B2="Lighting Designer"),"Pendant Lamps, Matcha Counter Lighting", IF(OR(A2="SignArt London",B2="Signage Designer"),"Custom Signage", IF(OR(A2="BronzeCraft"),"Teaware Fixture Prototypes", IF(OR(A2="HeritageUK"),"Heritage Compliance Files", IF(OR(A2="FireSafe Pro"),"Safety Certificates", IF(OR(A2="AccessCheck Ltd"),"Accessibility Audit Reports", IF(OR(A2="GreenSpace Assoc"),"Landscape Plant Samples", IF(OR(A2="Autodesk UK"),"CAD Software License", IF(OR(A2="PrintPro London"),"Blueprint Sets", IF(OR(A2="DHL UK"),"Courier Deliveries", IF(OR(A2="ToolHire London"),"Site Survey Tools Rental", "General Materials")))))))))))))) -> General Materials | K2: =IF(ISNUMBER(SEARCH("Bamboo",J2)),INDEX('Procurement and Deliveries'!D:D,MATCH("Bamboo Floor Planks",'Procurement and Deliveries'!A:A,0)), IF(ISNUMBER(SEARCH("Terrazzo",J2)),INDEX('Procurement and Deliveries'!D:D,MATCH("Terrazzo Tiles",'Procurement and Deliveries'!A:A,0)), IF(ISNUMBER(SEARCH("Lime-Wash",J2)),INDEX('Procurement and Deliveries'!D:D,MATCH("Lime-Wash Paint",'Procurement and Deliveries'!A:A,0)), IF(ISNUMBER(SEARCH("Pendant",J2)),INDEX('Procurement and Deliveries'!D:D,MATCH("Pendant Lamps",'Procurement and Deliveries'!A:A,0)), IF(ISNUMBER(SEARCH("Matcha",J2)),INDEX('Procurement and Deliveries'!D:D,MATCH("Matcha Counter Lighting",'Procurement and Deliveries'!A:A,0)), IF(ISNUMBER(SEARCH("Signage",J2)),INDEX('Procurement and Deliveries'!D:D,MATCH("Custom Signage",'Procurement and Deliveries'!A:A,0)), IF(ISNUMBER(SEARCH("Teaware",J2)),INDEX('Procurement and Deliveries'!D:D,MATCH("Teaware Fixture Prototypes",'Procurement and Deliveries'!A:A,0)), IF(ISNUMBER(SEARCH("Heritage",J2)),INDEX('Procurement and Deliveries'!D:D,MATCH("Heritage Compliance Files",'Procurement and Deliveries'!A:A,0)), IF(ISNUMBER(SEARCH("Safety",J2)),INDEX('Procurement and Deliveries'!D:D,MATCH("Safety Certificates",'Procurement and Deliveries'!A:A,0)), IF(ISNUMBER(SEARCH("Accessibility",J2)),INDEX('Procurement and Deliveries'!D:D,MATCH("Accessibility Audit Reports",'Procurement and Deliveries'!A:A,0)), IF(ISNUMBER(SEARCH("Landscape",J2)),INDEX('Procurement and Deliveries'!D:D,MATCH("Landscape Plant Samples",'Procurement and Deliveries'!A:A,0)), IF(ISNUMBER(SEARCH("CAD",J2)),INDEX('Procurement and Deliveries'!D:D,MATCH("CAD Software License",'Procurement and Deliveries'!A:A,0)), IF(ISNUMBER(SEARCH("Blueprint",J2)),INDEX('Procurement and Deliveries'!D:D,MATCH("Blueprint Sets",'Procurement and Deliveries'!A:A,0)), IF(ISNUMBER(SEARCH("Courier",J2)),INDEX('Procurement and Deliveries'!D:D,MATCH("Courier Deliveries",'Procurement and Deliveries'!A:A,0)), IF(ISNUMBER(SEARCH("Survey",J2)),INDEX('Procurement and Deliveries'!D:D,MATCH("Site Survey Tools Rental",'Procurement and Deliveries'!A:A,0)),""))))))))))))))) | L2: =IF(J2="General Materials","", IFERROR(INDEX('Procurement and Deliveries'!G:G,MATCH(LEFT(TRIM(J2),FIND(",",TRIM(J2)&",")-1),'Procurement and Deliveries'!A:A,0)),"No Match"))
A3: Tokkia Design Partners | B3: Interior Designer | C3: Interior Design Services | D3: 46118 | E3: 46122 | F3: 18000 | G3: 18000 | H3: =F3-G3 -> 0 | I3: paid | J3: =IF(OR(A3="EcoBuild Ltd",B3="Carpenter"),"Bamboo Floor Planks", IF(OR(A3="TerraFloor Supplies"),"Terrazzo Tiles, Terrazzo Sample Set", IF(OR(A3="EcoPaints UK"),"Lime-Wash Paint", IF(OR(A3="Lumina Studio",B3="Lighting Designer"),"Pendant Lamps, Matcha Counter Lighting", IF(OR(A3="SignArt London",B3="Signage Designer"),"Custom Signage", IF(OR(A3="BronzeCraft"),"Teaware Fixture Prototypes", IF(OR(A3="HeritageUK"),"Heritage Compliance Files", IF(OR(A3="FireSafe Pro"),"Safety Certificates", IF(OR(A3="AccessCheck Ltd"),"Accessibility Audit Reports", IF(OR(A3="GreenSpace Assoc"),"Landscape Plant Samples", IF(OR(A3="Autodesk UK"),"CAD Software License", IF(OR(A3="PrintPro London"),"Blueprint Sets", IF(OR(A3="DHL UK"),"Courier Deliveries", IF(OR(A3="ToolHire London"),"Site Survey Tools Rental", "General Materials")))))))))))))) -> General Materials | L3: =IF(J3="General Materials","", IFERROR(INDEX('Procurement and Deliveries'!G:G,MATCH(LEFT(TRIM(J3),FIND(",",TRIM(J3)&",")-1),'Procurement and Deliveries'!A:A,0)),"No Match"))
A4: EngStruct London | B4: Structural Engineer | C4: Structural Engineering | D4: 46120 | E4: 46124 | F4: 8000 | G4: 0 | H4: =F4-G4 -> 8000 | I4: pending | J4: =IF(OR(A4="EcoBuild Ltd",B4="Carpenter"),"Bamboo Floor Planks", IF(OR(A4="TerraFloor Supplies"),"Terrazzo Tiles, Terrazzo Sample Set", IF(OR(A4="EcoPaints UK"),"Lime-Wash Paint", IF(OR(A4="Lumina Studio",B4="Lighting Designer"),"Pendant Lamps, Matcha Counter Lighting", IF(OR(A4="SignArt London",B4="Signage Designer"),"Custom Signage", IF(OR(A4="BronzeCraft"),"Teaware Fixture Prototypes", IF(OR(A4="HeritageUK"),"Heritage Compliance Files", IF(OR(A4="FireSafe Pro"),"Safety Certificates", IF(OR(A4="AccessCheck Ltd"),"Accessibility Audit Reports", IF(OR(A4="GreenSpace Assoc"),"Landscape Plant Samples", IF(OR(A4="Autodesk UK"),"CAD Software License", IF(OR(A4="PrintPro London"),"Blueprint Sets", IF(OR(A4="DHL UK"),"Courier Deliveries", IF(OR(A4="ToolHire London"),"Site Survey Tools Rental", "General Materials")))))))))))))) -> General Materials | K4: =IF(ISNUMBER(SEARCH("Bamboo",J4)),INDEX('Procurement and Deliveries'!D:D,MATCH("Bamboo Floor Planks",'Procurement and Deliveries'!A:A,0)), IF(ISNUMBER(SEARCH("Terrazzo",J4)),INDEX('Procurement and Deliveries'!D:D,MATCH("Terrazzo Tiles",'Procurement and Deliveries'!A:A,0)), IF(ISNUMBER(SEARCH("Lime-Wash",J4)),INDEX('Procurement and Deliveries'!D:D,MATCH("Lime-Wash Paint",'Procurement and Deliveries'!A:A,0)), IF(ISNUMBER(SEARCH("Pendant",J4)),INDEX('Procurement and Deliveries'!D:D,MATCH("Pendant Lamps",'Procurement and Deliveries'!A:A,0)), IF(ISNUMBER(SEARCH("Matcha",J4)),INDEX('Procurement and Deliveries'!D:D,MATCH("Matcha Counter Lighting",'Procurement and Deliveries'!A:A,0)), IF(ISNUMBER(SEARCH("Signage",J4)),INDEX('Procurement and Deliveries'!D:D,MATCH("Custom Signage",'Procurement and Deliveries'!A:A,0)), IF(ISNUMBER(SEARCH("Teaware",J4)),INDEX('Procurement and Deliveries'!D:D,MATCH("Teaware Fixture Prototypes",'Procurement and Deliveries'!A:A,0)), IF(ISNUMBER(SEARCH("Heritage",J4)),INDEX('Procurement and Deliveries'!D:D,MATCH("Heritage Compliance Files",'Procurement and Deliveries'!A:A,0)), IF(ISNUMBER(SEARCH("Safety",J4)),INDEX('Procurement and Deliveries'!D:D,MATCH("Safety Certificates",'Procurement and Deliveries'!A:A,0)), IF(ISNUMBER(SEARCH("Accessibility",J4)),INDEX('Procurement and Deliveries'!D:D,MATCH("Accessibility Audit Reports",'Procurement and Deliveries'!A:A,0)), IF(ISNUMBER(SEARCH("Landscape",J4)),INDEX('Procurement and Deliveries'!D:D,MATCH("Landscape Plant Samples",'Procurement and Deliveries'!A:A,0)), IF(ISNUMBER(SEARCH("CAD",J4)),INDEX('Procurement and Deliveries'!D:D,MATCH("CAD Software License",'Procurement and Deliveries'!A:A,0)), IF(ISNUMBER(SEARCH("Blueprint",J4)),INDEX('Procurement and Deliveries'!D:D,MATCH("Blueprint Sets",'Procurement and Deliveries'!A:A,0)), IF(ISNUMBER(SEARCH("Courier",J4)),INDEX('Procurement and Deliveries'!D:D,MATCH("Courier Deliveries",'Procurement and Deliveries'!A:A,0)), IF(ISNUMBER(SEARCH("Survey",J4)),INDEX('Procurement and Deliveries'!D:D,MATCH("Site Survey Tools Rental",'Procurement and Deliveries'!A:A,0)),""))))))))))))))) | L4: =IF(J4="General Materials","", IFERROR(INDEX('Procurement and Deliveries'!G:G,MATCH(LEFT(TRIM(J4),FIND(",",TRIM(J4)&",")-1),'Procurement and Deliveries'!A:A,0)),"No Match"))
A5: MechEng UK | B5: MEP Engineer | C5: MEP Engineering Plans | D5: 46118 | E5: 46122 | F5: 6500 | G5: 6500 | H5: =F5-G5 -> 0 | I5: paid | J5: =IF(OR(A5="EcoBuild Ltd",B5="Carpenter"),"Bamboo Floor Planks", IF(OR(A5="TerraFloor Supplies"),"Terrazzo Tiles, Terrazzo Sample Set", IF(OR(A5="EcoPaints UK"),"Lime-Wash Paint", IF(OR(A5="Lumina Studio",B5="Lighting Designer"),"Pendant Lamps, Matcha Counter Lighting", IF(OR(A5="SignArt London",B5="Signage Designer"),"Custom Signage", IF(OR(A5="BronzeCraft"),"Teaware Fixture Prototypes", IF(OR(A5="HeritageUK"),"Heritage Compliance Files", IF(OR(A5="FireSafe Pro"),"Safety Certificates", IF(OR(A5="AccessCheck Ltd"),"Accessibility Audit Reports", IF(OR(A5="GreenSpace Assoc"),"Landscape Plant Samples", IF(OR(A5="Autodesk UK"),"CAD Software License", IF(OR(A5="PrintPro London"),"Blueprint Sets", IF(OR(A5="DHL UK"),"Courier Deliveries", IF(OR(A5="ToolHire London"),"Site Survey Tools Rental", "General Materials")))))))))))))) -> General Materials | L5: =IF(J5="General Materials","", IFERROR(INDEX('Procurement and Deliveries'!G:G,MATCH(LEFT(TRIM(J5),FIND(",",TRIM(J5)&",")-1),'Procurement and Deliveries'!A:A,0)),"No Match"))
A6: Camden Council | B6: Planning Authority | C6: Planning Application | D6: 46120 | E6: 46124 | F6: 4000 | G6: 4000 | H6: =F6-G6 -> 0 | I6: paid | J6: =IF(OR(A6="EcoBuild Ltd",B6="Carpenter"),"Bamboo Floor Planks", IF(OR(A6="TerraFloor Supplies"),"Terrazzo Tiles, Terrazzo Sample Set", IF(OR(A6="EcoPaints UK"),"Lime-Wash Paint", IF(OR(A6="Lumina Studio",B6="Lighting Designer"),"Pendant Lamps, Matcha Counter Lighting", IF(OR(A6="SignArt London",B6="Signage Designer"),"Custom Signage", IF(OR(A6="BronzeCraft"),"Teaware Fixture Prototypes", IF(OR(A6="HeritageUK"),"Heritage Compliance Files", IF(OR(A6="FireSafe Pro"),"Safety Certificates", IF(OR(A6="AccessCheck Ltd"),"Accessibility Audit Reports", IF(OR(A6="GreenSpace Assoc"),"Landscape Plant Samples", IF(OR(A6="Autodesk UK"),"CAD Software License", IF(OR(A6="PrintPro London"),"Blueprint Sets", IF(OR(A6="DHL UK"),"Courier Deliveries", IF(OR(A6="ToolHire London"),"Site Survey Tools Rental", "General Materials")))))))))))))) -> General Materials | K6: =IF(ISNUMBER(SEARCH("Bamboo",J6)),INDEX('Procurement and Deliveries'!D:D,MATCH("Bamboo Floor Planks",'Procurement and Deliveries'!A:A,0)), IF(ISNUMBER(SEARCH("Terrazzo",J6)),INDEX('Procurement and Deliveries'!D:D,MATCH("Terrazzo Tiles",'Procurement and Deliveries'!A:A,0)), IF(ISNUMBER(SEARCH("Lime-Wash",J6)),INDEX('Procurement and Deliveries'!D:D,MATCH("Lime-Wash Paint",'Procurement and Deliveries'!A:A,0)), IF(ISNUMBER(SEARCH("Pendant",J6)),INDEX('Procurement and Deliveries'!D:D,MATCH("Pendant Lamps",'Procurement and Deliveries'!A:A,0)), IF(ISNUMBER(SEARCH("Matcha",J6)),INDEX('Procurement and Deliveries'!D:D,MATCH("Matcha Counter Lighting",'Procurement and Deliveries'!A:A,0)), IF(ISNUMBER(SEARCH("Signage",J6)),INDEX('Procurement and Deliveries'!D:D,MATCH("Custom Signage",'Procurement and Deliveries'!A:A,0)), IF(ISNUMBER(SEARCH("Teaware",J6)),INDEX('Procurement and Deliveries'!D:D,MATCH("Teaware Fixture Prototypes",'Procurement and Deliveries'!A:A,0)), IF(ISNUMBER(SEARCH("Heritage",J6)),INDEX('Procurement and Deliveries'!D:D,MATCH("Heritage Compliance Files",'Procurement and Deliveries'!A:A,0)), IF(ISNUMBER(SEARCH("Safety",J6)),INDEX('Procurement and Deliveries'!D:D,MATCH("Safety Certificates",'Procurement and Deliveries'!A:A,0)), IF(ISNUMBER(SEARCH("Accessibility",J6)),INDEX('Procurement and Deliveries'!D:D,MATCH("Accessibility Audit Reports",'Procurement and Deliveries'!A:A,0)), IF(ISNUMBER(SEARCH("Landscape",J6)),INDEX('Procurement and Deliveries'!D:D,MATCH("Landscape Plant Samples",'Procurement and Deliveries'!A:A,0)), IF(ISNUMBER(SEARCH("CAD",J6)),INDEX('Procurement and Deliveries'!D:D,MATCH("CAD Software License",'Procurement and Deliveries'!A:A,0)), IF(ISNUMBER(SEARCH("Blueprint",J6)),INDEX('Procurement and Deliveries'!D:D,MATCH("Blueprint Sets",'Procurement and Deliveries'!A:A,0)), IF(ISNUMBER(SEARCH("Courier",J6)),INDEX('Procurement and Deliveries'!D:D,MATCH("Courier Deliveries",'Procurement and Deliveries'!A:A,0)), IF(ISNUMBER(SEARCH("Survey",J6)),INDEX('Procurement and Deliveries'!D:D,MATCH("Site Survey Tools Rental",'Procurement and Deliveries'!A:A,0)),""))))))))))))))) | L6: =IF(J6="General Materials","", IFERROR(INDEX('Procurement and Deliveries'!G:G,MATCH(LEFT(TRIM(J6),FIND(",",TRIM(J6)&",")-1),'Procurement and Deliveries'!A:A,0)),"No Match"))
A7: LABC London | B7: Building Control | C7: Building Regs Approval | D7: 46122 | E7: 46127 | F7: 2500 | G7: 2500 | H7: =F7-G7 -> 0 | I7: paid | J7: =IF(OR(A7="EcoBuild Ltd",B7="Carpenter"),"Bamboo Floor Planks", IF(OR(A7="TerraFloor Supplies"),"Terrazzo Tiles, Terrazzo Sample Set", IF(OR(A7="EcoPaints UK"),"Lime-Wash Paint", IF(OR(A7="Lumina Studio",B7="Lighting Designer"),"Pendant Lamps, Matcha Counter Lighting", IF(OR(A7="SignArt London",B7="Signage Designer"),"Custom Signage", IF(OR(A7="BronzeCraft"),"Teaware Fixture Prototypes", IF(OR(A7="HeritageUK"),"Heritage Compliance Files", IF(OR(A7="FireSafe Pro"),"Safety Certificates", IF(OR(A7="AccessCheck Ltd"),"Accessibility Audit Reports", IF(OR(A7="GreenSpace Assoc"),"Landscape Plant Samples", IF(OR(A7="Autodesk UK"),"CAD Software License", IF(OR(A7="PrintPro London"),"Blueprint Sets", IF(OR(A7="DHL UK"),"Courier Deliveries", IF(OR(A7="ToolHire London"),"Site Survey Tools Rental", "General Materials")))))))))))))) -> General Materials | L7: =IF(J7="General Materials","", IFERROR(INDEX('Procurement and Deliveries'!G:G,MATCH(LEFT(TRIM(J7),FIND(",",TRIM(J7)&",")-1),'Procurement and Deliveries'!A:A,0)),"No Match"))
A8: SurveyPro Ltd | B8: Surveyor | C8: Site Surveys | D8: 46113 | E8: 46120 | F8: 3000 | G8: 3000 | H8: =F8-G8 -> 0 | I8: paid | J8: =IF(OR(A8="EcoBuild Ltd",B8="Carpenter"),"Bamboo Floor Planks", IF(OR(A8="TerraFloor Supplies"),"Terrazzo Tiles, Terrazzo Sample Set", IF(OR(A8="EcoPaints UK"),"Lime-Wash Paint", IF(OR(A8="Lumina Studio",B8="Lighting Designer"),"Pendant Lamps, Matcha Counter Lighting", IF(OR(A8="SignArt London",B8="Signage Designer"),"Custom Signage", IF(OR(A8="BronzeCraft"),"Teaware Fixture Prototypes", IF(OR(A8="HeritageUK"),"Heritage Compliance Files", IF(OR(A8="FireSafe Pro"),"Safety Certificates", IF(OR(A8="AccessCheck Ltd"),"Accessibility Audit Reports", IF(OR(A8="GreenSpace Assoc"),"Landscape Plant Samples", IF(OR(A8="Autodesk UK"),"CAD Software License", IF(OR(A8="PrintPro London"),"Blueprint Sets", IF(OR(A8="DHL UK"),"Courier Deliveries", IF(OR(A8="ToolHire London"),"Site Survey Tools Rental", "General Materials")))))))))))))) -> General Materials | K8: =IF(ISNUMBER(SEARCH("Bamboo",J8)),INDEX('Procurement and Deliveries'!D:D,MATCH("Bamboo Floor Planks",'Procurement and Deliveries'!A:A,0)), IF(ISNUMBER(SEARCH("Terrazzo",J8)),INDEX('Procurement and Deliveries'!D:D,MATCH("Terrazzo Tiles",'Procurement and Deliveries'!A:A,0)), IF(ISNUMBER(SEARCH("Lime-Wash",J8)),INDEX('Procurement and Deliveries'!D:D,MATCH("Lime-Wash Paint",'Procurement and Deliveries'!A:A,0)), IF(ISNUMBER(SEARCH("Pendant",J8)),INDEX('Procurement and Deliveries'!D:D,MATCH("Pendant Lamps",'Procurement and Deliveries'!A:A,0)), IF(ISNUMBER(SEARCH("Matcha",J8)),INDEX('Procurement and Deliveries'!D:D,MATCH("Matcha Counter Lighting",'Procurement and Deliveries'!A:A,0)), IF(ISNUMBER(SEARCH("Signage",J8)),INDEX('Procurement and Deliveries'!D:D,MATCH("Custom Signage",'Procurement and Deliveries'!A:A,0)), IF(ISNUMBER(SEARCH("Teaware",J8)),INDEX('Procurement and Deliveries'!D:D,MATCH("Teaware Fixture Prototypes",'Procurement and Deliveries'!A:A,0)), IF(ISNUMBER(SEARCH("Heritage",J8)),INDEX('Procurement and Deliveries'!D:D,MATCH("Heritage Compliance Files",'Procurement and Deliveries'!A:A,0)), IF(ISNUMBER(SEARCH("Safety",J8)),INDEX('Procurement and Deliveries'!D:D,MATCH("Safety Certificates",'Procurement and Deliveries'!A:A,0)), IF(ISNUMBER(SEARCH("Accessibility",J8)),INDEX('Procurement and Deliveries'!D:D,MATCH("Accessibility Audit Reports",'Procurement and Deliveries'!A:A,0)), IF(ISNUMBER(SEARCH("Landscape",J8)),INDEX('Procurement and Deliveries'!D:D,MATCH("Landscape Plant Samples",'Procurement and Deliveries'!A:A,0)), IF(ISNUMBER(SEARCH("CAD",J8)),INDEX('Procurement and Deliveries'!D:D,MATCH("CAD Software License",'Procurement and Deliveries'!A:A,0)), IF(ISNUMBER(SEARCH("Blueprint",J8)),INDEX('Procurement and Deliveries'!D:D,MATCH("Blueprint Sets",'Procurement and Deliveries'!A:A,0)), IF(ISNUMBER(SEARCH("Courier",J8)),INDEX('Procurement and Deliveries'!D:D,MATCH("Courier Deliveries",'Procurement and Deliveries'!A:A,0)), IF(ISNUMBER(SEARCH("Survey",J8)),INDEX('Procurement and Deliveries'!D:D,MATCH("Site Survey Tools Rental",'Procurement and Deliveries'!A:A,0)),""))))))))))))))) | L8: =IF(J8="General Materials","", IFERROR(INDEX('Procurement and Deliveries'!G:G,MATCH(LEFT(TRIM(J8),FIND(",",TRIM(J8)&",")-1),'Procurement and Deliveries'!A:A,0)),"No Match"))
A9: RenderHub Studio | B9: Renderer | C9: 3D Renderings | D9: 46127 | E9: 46132 | F9: 5000 | G9: 0 | H9: =F9-G9 -> 5000 | I9: pending | J9: =IF(OR(A9="EcoBuild Ltd",B9="Carpenter"),"Bamboo Floor Planks", IF(OR(A9="TerraFloor Supplies"),"Terrazzo Tiles, Terrazzo Sample Set", IF(OR(A9="EcoPaints UK"),"Lime-Wash Paint", IF(OR(A9="Lumina Studio",B9="Lighting Designer"),"Pendant Lamps, Matcha Counter Lighting", IF(OR(A9="SignArt London",B9="Signage Designer"),"Custom Signage", IF(OR(A9="BronzeCraft"),"Teaware Fixture Prototypes", IF(OR(A9="HeritageUK"),"Heritage Compliance Files", IF(OR(A9="FireSafe Pro"),"Safety Certificates", IF(OR(A9="AccessCheck Ltd"),"Accessibility Audit Reports", IF(OR(A9="GreenSpace Assoc"),"Landscape Plant Samples", IF(OR(A9="Autodesk UK"),"CAD Software License", IF(OR(A9="PrintPro London"),"Blueprint Sets", IF(OR(A9="DHL UK"),"Courier Deliveries", IF(OR(A9="ToolHire London"),"Site Survey Tools Rental", "General Materials")))))))))))))) -> General Materials | L9: =IF(J9="General Materials","", IFERROR(INDEX('Procurement and Deliveries'!G:G,MATCH(LEFT(TRIM(J9),FIND(",",TRIM(J9)&",")-1),'Procurement and Deliveries'!A:A,0)),"No Match"))
A10: GreenSpace Assoc | B10: Landscape Consultant | C10: Landscape Consultancy | D10: 46113 | E10: 46119 | F10: 2000 | G10: 2000 | H10: =F10-G10 -> 0 | I10: paid | J10: =IF(OR(A10="EcoBuild Ltd",B10="Carpenter"),"Bamboo Floor Planks", IF(OR(A10="TerraFloor Supplies"),"Terrazzo Tiles, Terrazzo Sample Set", IF(OR(A10="EcoPaints UK"),"Lime-Wash Paint", IF(OR(A10="Lumina Studio",B10="Lighting Designer"),"Pendant Lamps, Matcha Counter Lighting", IF(OR(A10="SignArt London",B10="Signage Designer"),"Custom Signage", IF(OR(A10="BronzeCraft"),"Teaware Fixture Prototypes", IF(OR(A10="HeritageUK"),"Heritage Compliance Files", IF(OR(A10="FireSafe Pro"),"Safety Certificates", IF(OR(A10="AccessCheck Ltd"),"Accessibility Audit Reports", IF(OR(A10="GreenSpace Assoc"),"Landscape Plant Samples", IF(OR(A10="Autodesk UK"),"CAD Software License", IF(OR(A10="PrintPro London"),"Blueprint Sets", IF(OR(A10="DHL UK"),"Courier Deliveries", IF(OR(A10="ToolHire London"),"Site Survey Tools Rental", "General Materials")))))))))))))) -> Landscape Plant Samples | K10: =IF(ISNUMBER(SEARCH("Bamboo",J10)),INDEX('Procurement and Deliveries'!D:D,MATCH("Bamboo Floor Planks",'Procurement and Deliveries'!A:A,0)), IF(ISNUMBER(SEARCH("Terrazzo",J10)),INDEX('Procurement and Deliveries'!D:D,MATCH("Terrazzo Tiles",'Procurement and Deliveries'!A:A,0)), IF(ISNUMBER(SEARCH("Lime-Wash",J10)),INDEX('Procurement and Deliveries'!D:D,MATCH("Lime-Wash Paint",'Procurement and Deliveries'!A:A,0)), IF(ISNUMBER(SEARCH("Pendant",J10)),INDEX('Procurement and Deliveries'!D:D,MATCH("Pendant Lamps",'Procurement and Deliveries'!A:A,0)), IF(ISNUMBER(SEARCH("Matcha",J10)),INDEX('Procurement and Deliveries'!D:D,MATCH("Matcha Counter Lighting",'Procurement and Deliveries'!A:A,0)), IF(ISNUMBER(SEARCH("Signage",J10)),INDEX('Procurement and Deliveries'!D:D,MATCH("Custom Signage",'Procurement and Deliveries'!A:A,0)), IF(ISNUMBER(SEARCH("Teaware",J10)),INDEX('Procurement and Deliveries'!D:D,MATCH("Teaware Fixture Prototypes",'Procurement and Deliveries'!A:A,0)), IF(ISNUMBER(SEARCH("Heritage",J10)),INDEX('Procurement and Deliveries'!D:D,MATCH("Heritage Compliance Files",'Procurement and Deliveries'!A:A,0)), IF(ISNUMBER(SEARCH("Safety",J10)),INDEX('Procurement and Deliveries'!D:D,MATCH("Safety Certificates",'Procurement and Deliveries'!A:A,0)), IF(ISNUMBER(SEARCH("Accessibility",J10)),INDEX('Procurement and Deliveries'!D:D,MATCH("Accessibility Audit Reports",'Procurement and Deliveries'!A:A,0)), IF(ISNUMBER(SEARCH("Landscape",J10)),INDEX('Procurement and Deliveries'!D:D,MATCH("Landscape Plant Samples",'Procurement and Deliveries'!A:A,0)), IF(ISNUMBER(SEARCH("CAD",J10)),INDEX('Procurement and Deliveries'!D:D,MATCH("CAD Software License",'Procurement and Deliveries'!A:A,0)), IF(ISNUMBER(SEARCH("Blueprint",J10)),INDEX('Procurement and Deliveries'!D:D,MATCH("Blueprint Sets",'Procurement and Deliveries'!A:A,0)), IF(ISNUMBER(SEARCH("Courier",J10)),INDEX('Procurement and Deliveries'!D:D,MATCH("Courier Deliveries",'Procurement and Deliveries'!A:A,0)), IF(ISNUMBER(SEARCH("Survey",J10)),INDEX('Procurement and Deliveries'!D:D,MATCH("Site Survey Tools Rental",'Procurement and Deliveries'!A:A,0)),""))))))))))))))) -> 46077 | L10: =IF(J10="General Materials","", IFERROR(INDEX('Procurement and Deliveries'!G:G,MATCH(LEFT(TRIM(J10),FIND(",",TRIM(J10)&",")-1),'Procurement and Deliveries'!A:A,0)),"No Match")) -> delivered
A11: SoundEng Ltd | B11: Acoustic Consultant | C11: Acoustic Design | D11: 46130 | E11: 46134 | F11: 3500 | G11: 0 | H11: =F11-G11 -> 3500 | I11: pending | J11: =IF(OR(A11="EcoBuild Ltd",B11="Carpenter"),"Bamboo Floor Planks", IF(OR(A11="TerraFloor Supplies"),"Terrazzo Tiles, Terrazzo Sample Set", IF(OR(A11="EcoPaints UK"),"Lime-Wash Paint", IF(OR(A11="Lumina Studio",B11="Lighting Designer"),"Pendant Lamps, Matcha Counter Lighting", IF(OR(A11="SignArt London",B11="Signage Designer"),"Custom Signage", IF(OR(A11="BronzeCraft"),"Teaware Fixture Prototypes", IF(OR(A11="HeritageUK"),"Heritage Compliance Files", IF(OR(A11="FireSafe Pro"),"Safety Certificates", IF(OR(A11="AccessCheck Ltd"),"Accessibility Audit Reports", IF(OR(A11="GreenSpace Assoc"),"Landscape Plant Samples", IF(OR(A11="Autodesk UK"),"CAD Software License", IF(OR(A11="PrintPro London"),"Blueprint Sets", IF(OR(A11="DHL UK"),"Courier Deliveries", IF(OR(A11="ToolHire London"),"Site Survey Tools Rental", "General Materials")))))))))))))) -> General Materials | L11: =IF(J11="General Materials","", IFERROR(INDEX('Procurement and Deliveries'!G:G,MATCH(LEFT(TRIM(J11),FIND(",",TRIM(J11)&",")-1),'Procurement and Deliveries'!A:A,0)),"No Match"))
A12: EcoBuild Partners | B12: Sustainability Consultant | C12: Sustainability Audit | D12: 46122 | E12: 46126 | F12: 4000 | G12: 4000 | H12: =F12-G12 -> 0 | I12: paid | J12: =IF(OR(A12="EcoBuild Ltd",B12="Carpenter"),"Bamboo Floor Planks", IF(OR(A12="TerraFloor Supplies"),"Terrazzo Tiles, Terrazzo Sample Set", IF(OR(A12="EcoPaints UK"),"Lime-Wash Paint", IF(OR(A12="Lumina Studio",B12="Lighting Designer"),"Pendant Lamps, Matcha Counter Lighting", IF(OR(A12="SignArt London",B12="Signage Designer"),"Custom Signage", IF(OR(A12="BronzeCraft"),"Teaware Fixture Prototypes", IF(OR(A12="HeritageUK"),"Heritage Compliance Files", IF(OR(A12="FireSafe Pro"),"Safety Certificates", IF(OR(A12="AccessCheck Ltd"),"Accessibility Audit Reports", IF(OR(A12="GreenSpace Assoc"),"Landscape Plant Samples", IF(OR(A12="Autodesk UK"),"CAD Software License", IF(OR(A12="PrintPro London"),"Blueprint Sets", IF(OR(A12="DHL UK"),"Courier Deliveries", IF(OR(A12="ToolHire London"),"Site Survey Tools Rental", "General Materials")))))))))))))) -> General Materials | K12: =IF(ISNUMBER(SEARCH("Bamboo",J12)),INDEX('Procurement and Deliveries'!D:D,MATCH("Bamboo Floor Planks",'Procurement and Deliveries'!A:A,0)), IF(ISNUMBER(SEARCH("Terrazzo",J12)),INDEX('Procurement and Deliveries'!D:D,MATCH("Terrazzo Tiles",'Procurement and Deliveries'!A:A,0)), IF(ISNUMBER(SEARCH("Lime-Wash",J12)),INDEX('Procurement and Deliveries'!D:D,MATCH("Lime-Wash Paint",'Procurement and Deliveries'!A:A,0)), IF(ISNUMBER(SEARCH("Pendant",J12)),INDEX('Procurement and Deliveries'!D:D,MATCH("Pendant Lamps",'Procurement and Deliveries'!A:A,0)), IF(ISNUMBER(SEARCH("Matcha",J12)),INDEX('Procurement and Deliveries'!D:D,MATCH("Matcha Counter Lighting",'Procurement and Deliveries'!A:A,0)), IF(ISNUMBER(SEARCH("Signage",J12)),INDEX('Procurement and Deliveries'!D:D,MATCH("Custom Signage",'Procurement and Deliveries'!A:A,0)), IF(ISNUMBER(SEARCH("Teaware",J12)),INDEX('Procurement and Deliveries'!D:D,MATCH("Teaware Fixture Prototypes",'Procurement and Deliveries'!A:A,0)), IF(ISNUMBER(SEARCH("Heritage",J12)),INDEX('Procurement and Deliveries'!D:D,MATCH("Heritage Compliance Files",'Procurement and Deliveries'!A:A,0)), IF(ISNUMBER(SEARCH("Safety",J12)),INDEX('Procurement and Deliveries'!D:D,MATCH("Safety Certificates",'Procurement and Deliveries'!A:A,0)), IF(ISNUMBER(SEARCH("Accessibility",J12)),INDEX('Procurement and Deliveries'!D:D,MATCH("Accessibility Audit Reports",'Procurement and Deliveries'!A:A,0)), IF(ISNUMBER(SEARCH("Landscape",J12)),INDEX('Procurement and Deliveries'!D:D,MATCH("Landscape Plant Samples",'Procurement and Deliveries'!A:A,0)), IF(ISNUMBER(SEARCH("CAD",J12)),INDEX('Procurement and Deliveries'!D:D,MATCH("CAD Software License",'Procurement and Deliveries'!A:A,0)), IF(ISNUMBER(SEARCH("Blueprint",J12)),INDEX('Procurement and Deliveries'!D:D,MATCH("Blueprint Sets",'Procurement and Deliveries'!A:A,0)), IF(ISNUMBER(SEARCH("Courier",J12)),INDEX('Procurement and Deliveries'!D:D,MATCH("Courier Deliveries",'Procurement and Deliveries'!A:A,0)), IF(ISNUMBER(SEARCH("Survey",J12)),INDEX('Procurement and Deliveries'!D:D,MATCH("Site Survey Tools Rental",'Procurement and Deliveries'!A:A,0)),""))))))))))))))) | L12: =IF(J12="General Materials","", IFERROR(INDEX('Procurement and Deliveries'!G:G,MATCH(LEFT(TRIM(J12),FIND(",",TRIM(J12)&",")-1),'Procurement and Deliveries'!A:A,0)),"No Match"))
A13: QS Experts | B13: Quantity Surveyor | C13: Quantity Surveyor Services | D13: 46117 | E13: 46121 | F13: 7000 | G13: 7000 | H13: =F13-G13 -> 0 | I13: paid | J13: =IF(OR(A13="EcoBuild Ltd",B13="Carpenter"),"Bamboo Floor Planks", IF(OR(A13="TerraFloor Supplies"),"Terrazzo Tiles, Terrazzo Sample Set", IF(OR(A13="EcoPaints UK"),"Lime-Wash Paint", IF(OR(A13="Lumina Studio",B13="Lighting Designer"),"Pendant Lamps, Matcha Counter Lighting", IF(OR(A13="SignArt London",B13="Signage Designer"),"Custom Signage", IF(OR(A13="BronzeCraft"),"Teaware Fixture Prototypes", IF(OR(A13="HeritageUK"),"Heritage Compliance Files", IF(OR(A13="FireSafe Pro"),"Safety Certificates", IF(OR(A13="AccessCheck Ltd"),"Accessibility Audit Reports", IF(OR(A13="GreenSpace Assoc"),"Landscape Plant Samples", IF(OR(A13="Autodesk UK"),"CAD Software License", IF(OR(A13="PrintPro London"),"Blueprint Sets", IF(OR(A13="DHL UK"),"Courier Deliveries", IF(OR(A13="ToolHire London"),"Site Survey Tools Rental", "General Materials")))))))))))))) -> General Materials | L13: =IF(J13="General Materials","", IFERROR(INDEX('Procurement and Deliveries'!G:G,MATCH(LEFT(TRIM(J13),FIND(",",TRIM(J13)&",")-1),'Procurement and Deliveries'!A:A,0)),"No Match"))
A14: PMG London | B14: Project Manager | C14: Project Management | D14: 46113 | E14: 46142 | F14: 12000 | G14: 6000 | H14: =F14-G14 -> 6000 | I14: partial | J14: =IF(OR(A14="EcoBuild Ltd",B14="Carpenter"),"Bamboo Floor Planks", IF(OR(A14="TerraFloor Supplies"),"Terrazzo Tiles, Terrazzo Sample Set", IF(OR(A14="EcoPaints UK"),"Lime-Wash Paint", IF(OR(A14="Lumina Studio",B14="Lighting Designer"),"Pendant Lamps, Matcha Counter Lighting", IF(OR(A14="SignArt London",B14="Signage Designer"),"Custom Signage", IF(OR(A14="BronzeCraft"),"Teaware Fixture Prototypes", IF(OR(A14="HeritageUK"),"Heritage Compliance Files", IF(OR(A14="FireSafe Pro"),"Safety Certificates", IF(OR(A14="AccessCheck Ltd"),"Accessibility Audit Reports", IF(OR(A14="GreenSpace Assoc"),"Landscape Plant Samples", IF(OR(A14="Autodesk UK"),"CAD Software License", IF(OR(A14="PrintPro London"),"Blueprint Sets", IF(OR(A14="DHL UK"),"Courier Deliveries", IF(OR(A14="ToolHire London"),"Site Survey Tools Rental", "General Materials")))))))))))))) -> General Materials | K14: =IF(ISNUMBER(SEARCH("Bamboo",J14)),INDEX('Procurement and Deliveries'!D:D,MATCH("Bamboo Floor Planks",'Procurement and Deliveries'!A:A,0)), IF(ISNUMBER(SEARCH("Terrazzo",J14)),INDEX('Procurement and Deliveries'!D:D,MATCH("Terrazzo Tiles",'Procurement and Deliveries'!A:A,0)), IF(ISNUMBER(SEARCH("Lime-Wash",J14)),INDEX('Procurement and Deliveries'!D:D,MATCH("Lime-Wash Paint",'Procurement and Deliveries'!A:A,0)), IF(ISNUMBER(SEARCH("Pendant",J14)),INDEX('Procurement and Deliveries'!D:D,MATCH("Pendant Lamps",'Procurement and Deliveries'!A:A,0)), IF(ISNUMBER(SEARCH("Matcha",J14)),INDEX('Procurement and Deliveries'!D:D,MATCH("Matcha Counter Lighting",'Procurement and Deliveries'!A:A,0)), IF(ISNUMBER(SEARCH("Signage",J14)),INDEX('Procurement and Deliveries'!D:D,MATCH("Custom Signage",'Procurement and Deliveries'!A:A,0)), IF(ISNUMBER(SEARCH("Teaware",J14)),INDEX('Procurement and Deliveries'!D:D,MATCH("Teaware Fixture Prototypes",'Procurement and Deliveries'!A:A,0)), IF(ISNUMBER(SEARCH("Heritage",J14)),INDEX('Procurement and Deliveries'!D:D,MATCH("Heritage Compliance Files",'Procurement and Deliveries'!A:A,0)), IF(ISNUMBER(SEARCH("Safety",J14)),INDEX('Procurement and Deliveries'!D:D,MATCH("Safety Certificates",'Procurement and Deliveries'!A:A,0)), IF(ISNUMBER(SEARCH("Accessibility",J14)),INDEX('Procurement and Deliveries'!D:D,MATCH("Accessibility Audit Reports",'Procurement and Deliveries'!A:A,0)), IF(ISNUMBER(SEARCH("Landscape",J14)),INDEX('Procurement and Deliveries'!D:D,MATCH("Landscape Plant Samples",'Procurement and Deliveries'!A:A,0)), IF(ISNUMBER(SEARCH("CAD",J14)),INDEX('Procurement and Deliveries'!D:D,MATCH("CAD Software License",'Procurement and Deliveries'!A:A,0)), IF(ISNUMBER(SEARCH("Blueprint",J14)),INDEX('Procurement and Deliveries'!D:D,MATCH("Blueprint Sets",'Procurement and Deliveries'!A:A,0)), IF(ISNUMBER(SEARCH("Courier",J14)),INDEX('Procurement and Deliveries'!D:D,MATCH("Courier Deliveries",'Procurement and Deliveries'!A:A,0)), IF(ISNUMBER(SEARCH("Survey",J14)),INDEX('Procurement and Deliveries'!D:D,MATCH("Site Survey Tools Rental",'Procurement and Deliveries'!A:A,0)),""))))))))))))))) | L14: =IF(J14="General Materials","", IFERROR(INDEX('Procurement and Deliveries'!G:G,MATCH(LEFT(TRIM(J14),FIND(",",TRIM(J14)&",")-1),'Procurement and Deliveries'!A:A,0)),"No Match"))
A15: Lumina Studio | B15: Lighting Designer | C15: Lighting Design | D15: 46132 | E15: 46137 | F15: 4500 | G15: 0 | H15: =F15-G15 -> 4500 | I15: pending | J15: =IF(OR(A15="EcoBuild Ltd",B15="Carpenter"),"Bamboo Floor Planks", IF(OR(A15="TerraFloor Supplies"),"Terrazzo Tiles, Terrazzo Sample Set", IF(OR(A15="EcoPaints UK"),"Lime-Wash Paint", IF(OR(A15="Lumina Studio",B15="Lighting Designer"),"Pendant Lamps, Matcha Counter Lighting", IF(OR(A15="SignArt London",B15="Signage Designer"),"Custom Signage", IF(OR(A15="BronzeCraft"),"Teaware Fixture Prototypes", IF(OR(A15="HeritageUK"),"Heritage Compliance Files", IF(OR(A15="FireSafe Pro"),"Safety Certificates", IF(OR(A15="AccessCheck Ltd"),"Accessibility Audit Reports", IF(OR(A15="GreenSpace Assoc"),"Landscape Plant Samples", IF(OR(A15="Autodesk UK"),"CAD Software License", IF(OR(A15="PrintPro London"),"Blueprint Sets", IF(OR(A15="DHL UK"),"Courier Deliveries", IF(OR(A15="ToolHire London"),"Site Survey Tools Rental", "General Materials")))))))))))))) -> Pendant Lamps, Matcha Counter Lighting | L15: =IF(J15="General Materials","", IFERROR(INDEX('Procurement and Deliveries'!G:G,MATCH(LEFT(TRIM(J15),FIND(",",TRIM(J15)&",")-1),'Procurement and Deliveries'!A:A,0)),"No Match")) -> pending
A16: BronzeCraft | B16: Fabricator | C16: Fixture Prototyping | D16: 46122 | E16: 46128 | F16: 6000 | G16: 6000 | H16: =F16-G16 -> 0 | I16: paid | J16: =IF(OR(A16="EcoBuild Ltd",B16="Carpenter"),"Bamboo Floor Planks", IF(OR(A16="TerraFloor Supplies"),"Terrazzo Tiles, Terrazzo Sample Set", IF(OR(A16="EcoPaints UK"),"Lime-Wash Paint", IF(OR(A16="Lumina Studio",B16="Lighting Designer"),"Pendant Lamps, Matcha Counter Lighting", IF(OR(A16="SignArt London",B16="Signage Designer"),"Custom Signage", IF(OR(A16="BronzeCraft"),"Teaware Fixture Prototypes", IF(OR(A16="HeritageUK"),"Heritage Compliance Files", IF(OR(A16="FireSafe Pro"),"Safety Certificates", IF(OR(A16="AccessCheck Ltd"),"Accessibility Audit Reports", IF(OR(A16="GreenSpace Assoc"),"Landscape Plant Samples", IF(OR(A16="Autodesk UK"),"CAD Software License", IF(OR(A16="PrintPro London"),"Blueprint Sets", IF(OR(A16="DHL UK"),"Courier Deliveries", IF(OR(A16="ToolHire London"),"Site Survey Tools Rental", "General Materials")))))))))))))) -> Teaware Fixture Prototypes | K16: =IF(ISNUMBER(SEARCH("Bamboo",J16)),INDEX('Procurement and Deliveries'!D:D,MATCH("Bamboo Floor Planks",'Procurement and Deliveries'!A:A,0)), IF(ISNUMBER(SEARCH("Terrazzo",J16)),INDEX('Procurement and Deliveries'!D:D,MATCH("Terrazzo Tiles",'Procurement and Deliveries'!A:A,0)), IF(ISNUMBER(SEARCH("Lime-Wash",J16)),INDEX('Procurement and Deliveries'!D:D,MATCH("Lime-Wash Paint",'Procurement and Deliveries'!A:A,0)), IF(ISNUMBER(SEARCH("Pendant",J16)),INDEX('Procurement and Deliveries'!D:D,MATCH("Pendant Lamps",'Procurement and Deliveries'!A:A,0)), IF(ISNUMBER(SEARCH("Matcha",J16)),INDEX('Procurement and Deliveries'!D:D,MATCH("Matcha Counter Lighting",'Procurement and Deliveries'!A:A,0)), IF(ISNUMBER(SEARCH("Signage",J16)),INDEX('Procurement and Deliveries'!D:D,MATCH("Custom Signage",'Procurement and Deliveries'!A:A,0)), IF(ISNUMBER(SEARCH("Teaware",J16)),INDEX('Procurement and Deliveries'!D:D,MATCH("Teaware Fixture Prototypes",'Procurement and Deliveries'!A:A,0)), IF(ISNUMBER(SEARCH("Heritage",J16)),INDEX('Procurement and Deliveries'!D:D,MATCH("Heritage Compliance Files",'Procurement and Deliveries'!A:A,0)), IF(ISNUMBER(SEARCH("Safety",J16)),INDEX('Procurement and Deliveries'!D:D,MATCH("Safety Certificates",'Procurement and Deliveries'!A:A,0)), IF(ISNUMBER(SEARCH("Accessibility",J16)),INDEX('Procurement and Deliveries'!D:D,MATCH("Accessibility Audit Reports",'Procurement and Deliveries'!A:A,0)), IF(ISNUMBER(SEARCH("Landscape",J16)),INDEX('Procurement and Deliveries'!D:D,MATCH("Landscape Plant Samples",'Procurement and Deliveries'!A:A,0)), IF(ISNUMBER(SEARCH("CAD",J16)),INDEX('Procurement and Deliveries'!D:D,MATCH("CAD Software License",'Procurement and Deliveries'!A:A,0)), IF(ISNUMBER(SEARCH("Blueprint",J16)),INDEX('Procurement and Deliveries'!D:D,MATCH("Blueprint Sets",'Procurement and Deliveries'!A:A,0)), IF(ISNUMBER(SEARCH("Courier",J16)),INDEX('Procurement and Deliveries'!D:D,MATCH("Courier Deliveries",'Procurement and Deliveries'!A:A,0)), IF(ISNUMBER(SEARCH("Survey",J16)),INDEX('Procurement and Deliveries'!D:D,MATCH("Site Survey Tools Rental",'Procurement and Deliveries'!A:A,0)),""))))))))))))))) -> 46069 | L16: =IF(J16="General Materials","", IFERROR(INDEX('Procurement and Deliveries'!G:G,MATCH(LEFT(TRIM(J16),FIND(",",TRIM(J16)&",")-1),'Procurement and Deliveries'!A:A,0)),"No Match")) -> delivered
A17: HeritageUK | B17: Heritage Consultant | C17: Heritage Review | D17: 46117 | E17: 46140 | F17: 3500 | G17: 3500 | H17: =F17-G17 -> 0 | I17: paid | J17: =IF(OR(A17="EcoBuild Ltd",B17="Carpenter"),"Bamboo Floor Planks", IF(OR(A17="TerraFloor Supplies"),"Terrazzo Tiles, Terrazzo Sample Set", IF(OR(A17="EcoPaints UK"),"Lime-Wash Paint", IF(OR(A17="Lumina Studio",B17="Lighting Designer"),"Pendant Lamps, Matcha Counter Lighting", IF(OR(A17="SignArt London",B17="Signage Designer"),"Custom Signage", IF(OR(A17="BronzeCraft"),"Teaware Fixture Prototypes", IF(OR(A17="HeritageUK"),"Heritage Compliance Files", IF(OR(A17="FireSafe Pro"),"Safety Certificates", IF(OR(A17="AccessCheck Ltd"),"Accessibility Audit Reports", IF(OR(A17="GreenSpace Assoc"),"Landscape Plant Samples", IF(OR(A17="Autodesk UK"),"CAD Software License", IF(OR(A17="PrintPro London"),"Blueprint Sets", IF(OR(A17="DHL UK"),"Courier Deliveries", IF(OR(A17="ToolHire London"),"Site Survey Tools Rental", "General Materials")))))))))))))) -> Heritage Compliance Files | L17: =IF(J17="General Materials","", IFERROR(INDEX('Procurement and Deliveries'!G:G,MATCH(LEFT(TRIM(J17),FIND(",",TRIM(J17)&",")-1),'Procurement and Deliveries'!A:A,0)),"No Match")) -> delivered
A18: FireSafe Pro | B18: Fire Safety Engineer | C18: Fire Safety Engineering | D18: 46132 | E18: 46140 | F18: 4000 | G18: 0 | H18: =F18-G18 -> 4000 | I18: pending | J18: =IF(OR(A18="EcoBuild Ltd",B18="Carpenter"),"Bamboo Floor Planks", IF(OR(A18="TerraFloor Supplies"),"Terrazzo Tiles, Terrazzo Sample Set", IF(OR(A18="EcoPaints UK"),"Lime-Wash Paint", IF(OR(A18="Lumina Studio",B18="Lighting Designer"),"Pendant Lamps, Matcha Counter Lighting", IF(OR(A18="SignArt London",B18="Signage Designer"),"Custom Signage", IF(OR(A18="BronzeCraft"),"Teaware Fixture Prototypes", IF(OR(A18="HeritageUK"),"Heritage Compliance Files", IF(OR(A18="FireSafe Pro"),"Safety Certificates", IF(OR(A18="AccessCheck Ltd"),"Accessibility Audit Reports", IF(OR(A18="GreenSpace Assoc"),"Landscape Plant Samples", IF(OR(A18="Autodesk UK"),"CAD Software License", IF(OR(A18="PrintPro London"),"Blueprint Sets", IF(OR(A18="DHL UK"),"Courier Deliveries", IF(OR(A18="ToolHire London"),"Site Survey Tools Rental", "General Materials")))))))))))))) -> Safety Certificates | K18: =IF(ISNUMBER(SEARCH("Bamboo",J18)),INDEX('Procurement and Deliveries'!D:D,MATCH("Bamboo Floor Planks",'Procurement and Deliveries'!A:A,0)), IF(ISNUMBER(SEARCH("Terrazzo",J18)),INDEX('Procurement and Deliveries'!D:D,MATCH("Terrazzo Tiles",'Procurement and Deliveries'!A:A,0)), IF(ISNUMBER(SEARCH("Lime-Wash",J18)),INDEX('Procurement and Deliveries'!D:D,MATCH("Lime-Wash Paint",'Procurement and Deliveries'!A:A,0)), IF(ISNUMBER(SEARCH("Pendant",J18)),INDEX('Procurement and Deliveries'!D:D,MATCH("Pendant Lamps",'Procurement and Deliveries'!A:A,0)), IF(ISNUMBER(SEARCH("Matcha",J18)),INDEX('Procurement and Deliveries'!D:D,MATCH("Matcha Counter Lighting",'Procurement and Deliveries'!A:A,0)), IF(ISNUMBER(SEARCH("Signage",J18)),INDEX('Procurement and Deliveries'!D:D,MATCH("Custom Signage",'Procurement and Deliveries'!A:A,0)), IF(ISNUMBER(SEARCH("Teaware",J18)),INDEX('Procurement and Deliveries'!D:D,MATCH("Teaware Fixture Prototypes",'Procurement and Deliveries'!A:A,0)), IF(ISNUMBER(SEARCH("Heritage",J18)),INDEX('Procurement and Deliveries'!D:D,MATCH("Heritage Compliance Files",'Procurement and Deliveries'!A:A,0)), IF(ISNUMBER(SEARCH("Safety",J18)),INDEX('Procurement and Deliveries'!D:D,MATCH("Safety Certificates",'Procurement and Deliveries'!A:A,0)), IF(ISNUMBER(SEARCH("Accessibility",J18)),INDEX('Procurement and Deliveries'!D:D,MATCH("Accessibility Audit Reports",'Procurement and Deliveries'!A:A,0)), IF(ISNUMBER(SEARCH("Landscape",J18)),INDEX('Procurement and Deliveries'!D:D,MATCH("Landscape Plant Samples",'Procurement and Deliveries'!A:A,0)), IF(ISNUMBER(SEARCH("CAD",J18)),INDEX('Procurement and Deliveries'!D:D,MATCH("CAD Software License",'Procurement and Deliveries'!A:A,0)), IF(ISNUMBER(SEARCH("Blueprint",J18)),INDEX('Procurement and Deliveries'!D:D,MATCH("Blueprint Sets",'Procurement and Deliveries'!A:A,0)), IF(ISNUMBER(SEARCH("Courier",J18)),INDEX('Procurement and Deliveries'!D:D,MATCH("Courier Deliveries",'Procurement and Deliveries'!A:A,0)), IF(ISNUMBER(SEARCH("Survey",J18)),INDEX('Procurement and Deliveries'!D:D,MATCH("Site Survey Tools Rental",'Procurement and Deliveries'!A:A,0)),""))))))))))))))) -> 46081 | L18: =IF(J18="General Materials","", IFERROR(INDEX('Procurement and Deliveries'!G:G,MATCH(LEFT(TRIM(J18),FIND(",",TRIM(J18)&",")-1),'Procurement and Deliveries'!A:A,0)),"No Match")) -> pending
A19: AccessCheck Ltd | B19: Accessibility Consultant | C19: Accessibility Audit | D19: 46122 | E19: 46131 | F19: 2500 | G19: 2500 | H19: =F19-G19 -> 0 | I19: paid | J19: =IF(OR(A19="EcoBuild Ltd",B19="Carpenter"),"Bamboo Floor Planks", IF(OR(A19="TerraFloor Supplies"),"Terrazzo Tiles, Terrazzo Sample Set", IF(OR(A19="EcoPaints UK"),"Lime-Wash Paint", IF(OR(A19="Lumina Studio",B19="Lighting Designer"),"Pendant Lamps, Matcha Counter Lighting", IF(OR(A19="SignArt London",B19="Signage Designer"),"Custom Signage", IF(OR(A19="BronzeCraft"),"Teaware Fixture Prototypes", IF(OR(A19="HeritageUK"),"Heritage Compliance Files", IF(OR(A19="FireSafe Pro"),"Safety Certificates", IF(OR(A19="AccessCheck Ltd"),"Accessibility Audit Reports", IF(OR(A19="GreenSpace Assoc"),"Landscape Plant Samples", IF(OR(A19="Autodesk UK"),"CAD Software License", IF(OR(A19="PrintPro London"),"Blueprint Sets", IF(OR(A19="DHL UK"),"Courier Deliveries", IF(OR(A19="ToolHire London"),"Site Survey Tools Rental", "General Materials")))))))))))))) -> Accessibility Audit Reports | L19: =IF(J19="General Materials","", IFERROR(INDEX('Procurement and Deliveries'!G:G,MATCH(LEFT(TRIM(J19),FIND(",",TRIM(J19)&",")-1),'Procurement and Deliveries'!A:A,0)),"No Match")) -> delivered
A20: SignArt London | B20: Signage Designer | C20: Signage & Graphics | D20: 46114 | E20: 46118 | F20: 3000 | G20: 3000 | H20: =F20-G20 -> 0 | I20: paid | J20: =IF(OR(A20="EcoBuild Ltd",B20="Carpenter"),"Bamboo Floor Planks", IF(OR(A20="TerraFloor Supplies"),"Terrazzo Tiles, Terrazzo Sample Set", IF(OR(A20="EcoPaints UK"),"Lime-Wash Paint", IF(OR(A20="Lumina Studio",B20="Lighting Designer"),"Pendant Lamps, Matcha Counter Lighting", IF(OR(A20="SignArt London",B20="Signage Designer"),"Custom Signage", IF(OR(A20="BronzeCraft"),"Teaware Fixture Prototypes", IF(OR(A20="HeritageUK"),"Heritage Compliance Files", IF(OR(A20="FireSafe Pro"),"Safety Certificates", IF(OR(A20="AccessCheck Ltd"),"Accessibility Audit Reports", IF(OR(A20="GreenSpace Assoc"),"Landscape Plant Samples", IF(OR(A20="Autodesk UK"),"CAD Software License", IF(OR(A20="PrintPro London"),"Blueprint Sets", IF(OR(A20="DHL UK"),"Courier Deliveries", IF(OR(A20="ToolHire London"),"Site Survey Tools Rental", "General Materials")))))))))))))) -> Custom Signage | K20: =IF(ISNUMBER(SEARCH("Bamboo",J20)),INDEX('Procurement and Deliveries'!D:D,MATCH("Bamboo Floor Planks",'Procurement and Deliveries'!A:A,0)), IF(ISNUMBER(SEARCH("Terrazzo",J20)),INDEX('Procurement and Deliveries'!D:D,MATCH("Terrazzo Tiles",'Procurement and Deliveries'!A:A,0)), IF(ISNUMBER(SEARCH("Lime-Wash",J20)),INDEX('Procurement and Deliveries'!D:D,MATCH("Lime-Wash Paint",'Procurement and Deliveries'!A:A,0)), IF(ISNUMBER(SEARCH("Pendant",J20)),INDEX('Procurement and Deliveries'!D:D,MATCH("Pendant Lamps",'Procurement and Deliveries'!A:A,0)), IF(ISNUMBER(SEARCH("Matcha",J20)),INDEX('Procurement and Deliveries'!D:D,MATCH("Matcha Counter Lighting",'Procurement and Deliveries'!A:A,0)), IF(ISNUMBER(SEARCH("Signage",J20)),INDEX('Procurement and Deliveries'!D:D,MATCH("Custom Signage",'Procurement and Deliveries'!A:A,0)), IF(ISNUMBER(SEARCH("Teaware",J20)),INDEX('Procurement and Deliveries'!D:D,MATCH("Teaware Fixture Prototypes",'Procurement and Deliveries'!A:A,0)), IF(ISNUMBER(SEARCH("Heritage",J20)),INDEX('Procurement and Deliveries'!D:D,MATCH("Heritage Compliance Files",'Procurement and Deliveries'!A:A,0)), IF(ISNUMBER(SEARCH("Safety",J20)),INDEX('Procurement and Deliveries'!D:D,MATCH("Safety Certificates",'Procurement and Deliveries'!A:A,0)), IF(ISNUMBER(SEARCH("Accessibility",J20)),INDEX('Procurement and Deliveries'!D:D,MATCH("Accessibility Audit Reports",'Procurement and Deliveries'!A:A,0)), IF(ISNUMBER(SEARCH("Landscape",J20)),INDEX('Procurement and Deliveries'!D:D,MATCH("Landscape Plant Samples",'Procurement and Deliveries'!A:A,0)), IF(ISNUMBER(SEARCH("CAD",J20)),INDEX('Procurement and Deliveries'!D:D,MATCH("CAD Software License",'Procurement and Deliveries'!A:A,0)), IF(ISNUMBER(SEARCH("Blueprint",J20)),INDEX('Procurement and Deliveries'!D:D,MATCH("Blueprint Sets",'Procurement and Deliveries'!A:A,0)), IF(ISNUMBER(SEARCH("Courier",J20)),INDEX('Procurement and Deliveries'!D:D,MATCH("Courier Deliveries",'Procurement and Deliveries'!A:A,0)), IF(ISNUMBER(SEARCH("Survey",J20)),INDEX('Procurement and Deliveries'!D:D,MATCH("Site Survey Tools Rental",'Procurement and Deliveries'!A:A,0)),""))))))))))))))) -> 46071 | L20: =IF(J20="General Materials","", IFERROR(INDEX('Procurement and Deliveries'!G:G,MATCH(LEFT(TRIM(J20),FIND(",",TRIM(J20)&",")-1),'Procurement and Deliveries'!A:A,0)),"No Match")) -> delivered
A21: Internal Reserve | B21: Design Revisions | C21: Design Adjustments | D21: 46132 | E21: 46139 | F21: 10800 | G21: 0 | H21: =F21-G21 -> 10800 | I21: pending | J21: =IF(OR(A21="EcoBuild Ltd",B21="Carpenter"),"Bamboo Floor Planks", IF(OR(A21="TerraFloor Supplies"),"Terrazzo Tiles, Terrazzo Sample Set", IF(OR(A21="EcoPaints UK"),"Lime-Wash Paint", IF(OR(A21="Lumina Studio",B21="Lighting Designer"),"Pendant Lamps, Matcha Counter Lighting", IF(OR(A21="SignArt London",B21="Signage Designer"),"Custom Signage", IF(OR(A21="BronzeCraft"),"Teaware Fixture Prototypes", IF(OR(A21="HeritageUK"),"Heritage Compliance Files", IF(OR(A21="FireSafe Pro"),"Safety Certificates", IF(OR(A21="AccessCheck Ltd"),"Accessibility Audit Reports", IF(OR(A21="GreenSpace Assoc"),"Landscape Plant Samples", IF(OR(A21="Autodesk UK"),"CAD Software License", IF(OR(A21="PrintPro London"),"Blueprint Sets", IF(OR(A21="DHL UK"),"Courier Deliveries", IF(OR(A21="ToolHire London"),"Site Survey Tools Rental", "General Materials")))))))))))))) -> General Materials | L21: =IF(J21="General Materials","", IFERROR(INDEX('Procurement and Deliveries'!G:G,MATCH(LEFT(TRIM(J21),FIND(",",TRIM(J21)&",")-1),'Procurement and Deliveries'!A:A,0)),"No Match"))

Sheet Procurement and Deliveries
A1: Item | B1: Supplier | C1: Order Date | D1: Expected Delivery | E1: Received Date | F1: Quantity | G1: Status | H1: Invoice # | I1: Notes
A2: Bamboo Floor Planks | B2: Eco Build Ltd | C2: 46063 | D2: 46073 | E2: 46074 | F2: 200 | G2: delivered (late) | H2: INV 1025
A3: Terrazzo Tiles | B3: TerraFloor Supplies | C3: 46068 | D3: 46078 | E3: 46078 | F3: 300 | G3: delivered | H3: INV 1032
A4: Lime-Wash Paint | B4: EcoPaints UK | C4: 46065 | D4: 46075 | E4: 46074 | F4: 50 | G4: delivered | H4: INV 1029
A5: Pendant Lamps | B5: Luminaa Studio | C5: 46067 | D5: 46080 | F5: 20 | G5: pending | H5: INV 1040
A6: Custom Signage | B6: SignArt London | C6: 46061 | D6: 46071 | E6: 46070 | F6: 10 | G6: delivered | H6: INV 1019
A7: Teaware Fixture Prototypes | B7: BronzeCraft | C7: 46063 | D7: 46069 | E7: 46069 | F7: 5 | G7: delivered | H7: INV 1020
A8: Matcha Counter Lighting | B8: Luminaa Studio | C8: 46071 | D8: 46078 | F8: 8 | G8: pending | H8: INV 1042
A9: Terrazzo Sample Set | B9: TerraFloora Supplies | C9: 46064 | D9: 46073 | E9: 46072 | F9: 10 | G9: delivered | H9: INV 1030
A10: Heritage Compliance Files | B10: HeritageUK | C10: 46063 | D10: 46068 | E10: 46068 | F10: 3 | G10: delivered | H10: INV 1028
A11: Safety Certificates | B11: FireSafe Pro | C11: 46067 | D11: 46081 | F11: 1 | G11: pending | H11: INV 1044
A12: Accessibility Audit Reports | B12: AccessCheck Ltd | C12: 46065 | D12: 46072 | E12: 46072 | F12: 2 | G12: delivered | H12: INV 1033
A13: Landscape Plant Samples | B13: GreenSpace Assoc | C13: 46067 | D13: 46077 | E13: 46077 | F13: 50 | G13: delivered | H13: INV 1041
A14: CAD Software License | B14: Autodesk UK | C14: 46054 | D14: 46054 | E14: 46054 | F14: 1 | G14: delivered | H14: INV 1005
A15: Blueprint Sets | B15: PrintPro London | C15: 46063 | D15: 46070 | E15: 46070 | F15: 200 | G15: delivered | H15: INV 1027
A16: Courier Deliveries | B16: DHL UK | C16: 46066 | D16: 46079 | F16: 15 | G16: pending | H16: INV 1043
A17: Site Survey Tools Rental | B17: ToolHire London | C17: 46057 | D17: 46063 | E17: 46062 | F17: 15 | G17: delivered | H17: INV 1012
A23: Procurement Summary | D23: Label
A24: Total Items Ordered | B24: =COUNTA(A2:A100) -> 21 | D24: Delivered (On Time) | E24: =COUNTIF(G2:G100,"Delivered") -> 11
A25: Pending Deliveries | B25: =COUNTIF(G2:G100,"Pending") -> 4 | D25: Pending | E25: =COUNTIF(G2:G100,"Pending") -> 4
A26: Delivered (Late) | B26: =COUNTIF(G2:G100,"Delivered (Late)") -> 1 | D26: Delivered (Late) | E26: =COUNTIF(G2:G100,"Delivered (Late)") -> 1
A27: Percent Delivered (On Time) | B27: =COUNTIF(G2:G100,"Delivered")/COUNTA(A2:A22) -> 0.6875

Sheet Dashboard
A1: TOKKIA MATCHA HOUSE - PROJECT DASHBOARD
A2: Total Budget | B2: =SUM('Cost and Budget Tracking'!G:G) -> 338200
A3: Total Spent | B3: =SUM('Cost and Budget Tracking'!F:F) -> 308080
A4: Remaining Budget | B4: =B2-B3 -> 30120
A5: Percentage of Budget Used | B5: =B3/B2 -> 0.91094027
A6: Over Budget Items | B6: =COUNTIF('Cost and Budget Tracking'!H:H,"<0") -> 0
A7: Paid Items | B7: =COUNTIF('Cost and Budget Tracking'!I:I,"Paid") -> 19
A11: Top 5 Expense Categories
A12: Design | B12: =SUMIF('Cost and Budget Tracking'!A:A,A12,'Cost and Budget Tracking'!F:F) -> 88800 | C12: =B12/$B$3 -> 0.28823682
A13: Engineering & Consulting | B13: =SUMIF('Cost and Budget Tracking'!A:A,A13,'Cost and Budget Tracking'!F:F) -> 30500 | C13: =B13/$B$3 -> 0.09900026
A14: Materials | B14: =SUMIF('Cost and Budget Tracking'!A:A,A14,'Cost and Budget Tracking'!F:F) -> 10500 | C14: =B14/$B$3 -> 0.034082057
A15: Permits & Approvals | B15: =SUMIF('Cost and Budget Tracking'!A:A,A15,'Cost and Budget Tracking'!F:F) -> 9500 | C15: =B15/$B$3 -> 0.030836146
A16: Fixtures & Equipment | B16: =SUMIF('Cost and Budget Tracking'!A:A,A16,'Cost and Budget Tracking'!F:F) -> 14740 | C16: =B16/$B$3 -> 0.047844716
